CHANGES
MANIFEST.in
README.rst
pyplete.py
setup.py
pyplete.egg-info/PKG-INFO
pyplete.egg-info/SOURCES.txt
pyplete.egg-info/dependency_links.txt
pyplete.egg-info/not-zip-safe
pyplete.egg-info/top_level.txt