Metadata-Version: 1.0
Name: pyplete
Version: 0.0.2
Summary: PYPLETE (PYthon autocomPLETE) is a interface to autocomplete in python
Home-page: https://github.com/goinnn/pyplete
Author: Pablo Martin
Author-email: goinnn@gmail.com
License: GNU Lesser General Public License
Keywords: pyplete,python,autocomplete,python autocomplete,python analizer
Platform: UNKNOWN
Classifier: Development Status :: 4 - Beta
Classifier: Environment :: Plugins
Classifier: Intended Audience :: Developers
Classifier: Natural Language :: English
Classifier: Programming Language :: Python :: 2.6
Classifier: Topic :: Software Development
